g2p_en/__init__.py
g2p_en/checkpoint20.npz
g2p_en/expand.py
g2p_en/g2p.py
g2p_en/homographs.en
g2p_en-2.1.0.dist-info/LICENSE.txt
g2p_en-2.1.0.dist-info/METADATA
g2p_en-2.1.0.dist-info/WHEEL
g2p_en-2.1.0.dist-info/top_level.txt
g2p_en-2.1.0.dist-info/RECORD
