Metadata-Version: 1.1
Name: g2p-en
Version: 2.1.0
Summary: A Simple Python Module for English Grapheme To Phoneme Conversion
Home-page: https://github.com/Kyubyong/g2p
Author: Kyubyong Park & Jongseok Kim
Author-email: kbpark.linguist@gmail.com
License: Apache Software License
Download-URL: https://github.com/Kyubyong/g2p/archive/1.0.0.tar.gz
Keywords: g2p,g2p_en,g2pE
Platform: UNKNOWN
